sardine/UserConfig.py
sardine/__init__.py
sardine/__main__.py
sardine/console.py
sardine/runners.py
sardine_core/__init__.py
sardine_core/fish_bowl.py
sardine_core/run.py
sardine_core/base/__init__.py
sardine_core/base/clock.py
sardine_core/base/handler.py
sardine_core/base/parser.py
sardine_core/base/runner.py
sardine_core/cli/__init__.py
sardine_core/cli/__main__.py
sardine_core/cli/main.py
sardine_core/clock/__init__.py
sardine_core/clock/internal_clock.py
sardine_core/clock/link_clock.py
sardine_core/clock/time.py
sardine_core/event_loop/__init__.py
sardine_core/event_loop/loop.py
sardine_core/event_loop/mixin.py
sardine_core/event_loop/policy.py
sardine_core/event_loop/sansio.py
sardine_core/handlers/__init__.py
sardine_core/handlers/midi.py
sardine_core/handlers/midi_in.py
sardine_core/handlers/missile.py
sardine_core/handlers/osc.py
sardine_core/handlers/osc_in.py
sardine_core/handlers/osc_loop.py
sardine_core/handlers/player.py
sardine_core/handlers/sender.py
sardine_core/handlers/superdirt.py
sardine_core/handlers/sleep_handler/__init__.py
sardine_core/handlers/sleep_handler/time_handle.py
sardine_core/io/UserConfig.py
sardine_core/io/__init__.py
sardine_core/logger/__init__.py
sardine_core/logger/logger.py
sardine_core/scheduler/__init__.py
sardine_core/scheduler/async_runner.py
sardine_core/scheduler/constants.py
sardine_core/scheduler/errors.py
sardine_core/scheduler/scheduler.py
sardine_core/sequences/__init__.py
sardine_core/sequences/chance.py
sardine_core/sequences/iterators.py
sardine_core/sequences/sequence.py
sardine_core/sequences/variables.py
sardine_core/sequences/sardine_parser/__init__.py
sardine_core/sequences/sardine_parser/chord.py
sardine_core/sequences/sardine_parser/funclib.py
sardine_core/sequences/sardine_parser/list_parser.py
sardine_core/sequences/sardine_parser/sardine.lark
sardine_core/sequences/sardine_parser/tree_calc.py
sardine_core/sequences/sardine_parser/utils.py
sardine_core/sequences/tidal_parser/__init__.py
sardine_system-0.4.0.dist-info/LICENSE.txt
sardine_system-0.4.0.dist-info/METADATA
sardine_system-0.4.0.dist-info/WHEEL
sardine_system-0.4.0.dist-info/entry_points.txt
sardine_system-0.4.0.dist-info/top_level.txt
sardine_system-0.4.0.dist-info/RECORD
