Metadata-Version: 2.1
Name: sardine-system
Version: 0.4.0
Summary: Python's missing algorave module
Author: Raphaël Forment, thegamecracks
Author-email: raphael.forment@gmail.com
License: GPL-3.0-only
Project-URL: Homepage, https://sardine.raphaelforment.fr
Project-URL: Documentation, https://sardine.raphaelforment.fr
Project-URL: Source Code, https://github.com/Bubobubobubobubo/sardine
Project-URL: Bug Tracker, https://github.com/Bubobubobubobubo/sardine/issues
Keywords: algorave,live-coding,music,patterns
Classifier: Development Status :: 3 - Alpha
Classifier: Framework :: AsyncIO
Classifier: Intended Audience :: End Users/Desktop
Classifier: Intended Audience :: Science/Research
Classifier: License :: OSI Approved
Classifier: License :: OSI Approved :: GNU General Public License v3 (GPLv3)
Classifier: Programming Language :: Python
Classifier: Programming Language :: Python :: 3
Classifier: Programming Language :: Python :: 3.10
Classifier: Programming Language :: Python :: 3.11
Classifier: Topic :: Artistic Software
Classifier: Topic :: Multimedia
Classifier: Topic :: Multimedia :: Sound/Audio
Classifier: Topic :: Multimedia :: Sound/Audio :: MIDI
Requires-Python: >=3.10
License-File: LICENSE.txt
Requires-Dist: ziffers (>=0.0.1)
Requires-Dist: parsimonious (>=0.10.0)
Requires-Dist: Click (>=8.1.3)
Requires-Dist: LinkPython-extern (>=1.0.2)
Requires-Dist: python-rtmidi (>=1.4.9)
Requires-Dist: inquirerpy (>=0.3.4)
Requires-Dist: easing-functions (>=1.0.4)
Requires-Dist: mido (>=1.2)
Requires-Dist: osc4py3 (>=1.0.8)
Requires-Dist: appdirs (>=1.4)
Requires-Dist: psutil (>=5.9)
Requires-Dist: rich (>=12.5)
Requires-Dist: lark (>=1.1)
Requires-Dist: exceptiongroup (>=1.0.4)
Requires-Dist: uvloop (>=0.16) ; sys_platform != "win32"
Provides-Extra: dev
Requires-Dist: black (>=22.8) ; extra == 'dev'
Requires-Dist: pylint (>=2.15) ; extra == 'dev'
Requires-Dist: pytest (>=7.2.0) ; extra == 'dev'
Requires-Dist: pytest-asyncio (>=0.20.2) ; extra == 'dev'
Provides-Extra: profile
Requires-Dist: yappi (>=1.4.0) ; extra == 'profile'
